investos/__init__.py
investos/portfolio/__init__.py
investos/portfolio/backtest_controller.py
investos/portfolio/constraint_model/__init__.py
investos/portfolio/constraint_model/base_constraint.py
investos/portfolio/constraint_model/factor_constraint.py
investos/portfolio/constraint_model/leverage_constraint.py
investos/portfolio/constraint_model/long_constraint.py
investos/portfolio/constraint_model/return_constraint.py
investos/portfolio/constraint_model/trade_constraint.py
investos/portfolio/constraint_model/weight_constraint.py
investos/portfolio/cost_model/__init__.py
investos/portfolio/cost_model/base_cost.py
investos/portfolio/cost_model/short_holding_cost.py
investos/portfolio/cost_model/trading_cost.py
investos/portfolio/result/__init__.py
investos/portfolio/result/base_result.py
investos/portfolio/result/save_result.py
investos/portfolio/result/weights_result.py
investos/portfolio/risk_model/__init__.py
investos/portfolio/risk_model/base_risk.py
investos/portfolio/risk_model/factor_risk.py
investos/portfolio/risk_model/risk_util.py
investos/portfolio/risk_model/stat_factor_risk.py
investos/portfolio/strategy/__init__.py
investos/portfolio/strategy/base_strategy.py
investos/portfolio/strategy/rank_long_short.py
investos/portfolio/strategy/spo.py
investos/portfolio/strategy/spo_tranches.py
investos/portfolio/strategy/spo_weights.py
investos/util.py
investos/utils/__init__.py
investos/utils/hydrate.py
investos-0.9.2.dist-info/LICENSE
investos-0.9.2.dist-info/METADATA
investos-0.9.2.dist-info/WHEEL
investos-0.9.2.dist-info/RECORD
