Metadata-Version: 2.1
Name: investos
Version: 0.9.2
Summary: Reliable backtesting and portfolio optimization for investors who want to focus on generating alpha
Home-page: https://investos.io/
License: MIT
Keywords: investing,alpha,backtesting,portfolio,optimization,forecastos
Author: Charlie Reese
Requires-Python: >=3.9,<4.0
Classifier: Development Status :: 4 - Beta
Classifier: Intended Audience :: Developers
Classifier: Intended Audience :: Financial and Insurance Industry
Classifier: License :: OSI Approved :: MIT License
Classifier: Natural Language :: English
Classifier: Operating System :: OS Independent
Classifier: Programming Language :: Python :: 3
Classifier: Programming Language :: Python :: 3.9
Classifier: Programming Language :: Python :: 3.10
Classifier: Programming Language :: Python :: 3.11
Classifier: Programming Language :: Python :: 3.12
Classifier: Programming Language :: Python :: 3 :: Only
Classifier: Programming Language :: Python :: 3.8
Classifier: Topic :: Office/Business :: Financial :: Investment
Classifier: Topic :: Software Development :: Testing
Requires-Dist: aiobotocore (>=2.13.2,<3.0.0)
Requires-Dist: cvxpy (>=1.5.4,<2.0.0)
Requires-Dist: dask (>=2024.8.0,<2025.0.0)
Requires-Dist: dask-cloudprovider (>=2022.10.0,<2023.0.0)
Requires-Dist: forecastos (>=0.2.0,<0.3.0)
Requires-Dist: numpy (>=1.24.3)
Requires-Dist: pandas (>=2.0.1,<3.0.0)
Requires-Dist: requests (>=2.31.0,<3.0.0)
Requires-Dist: statsmodels (>=0.14.2,<0.15.0)
Project-URL: Documentation, https://investos.readthedocs.io/en/latest/
Project-URL: Repository, https://github.com/forecastos/investos
